LICENSE
MANIFEST.in
README.md
setup.py
e2e_cli/__init__.py
e2e_cli/commands_routing.py
e2e_cli/main.py
e2e_cli/man_display.py
e2e_cli.egg-info/PKG-INFO
e2e_cli.egg-info/SOURCES.txt
e2e_cli.egg-info/dependency_links.txt
e2e_cli.egg-info/entry_points.txt
e2e_cli.egg-info/requires.txt
e2e_cli.egg-info/top_level.txt
e2e_cli/auto_scaling/__init__.py
e2e_cli/auto_scaling/auto_scaling.py
e2e_cli/auto_scaling/autoscaling_routing.py
e2e_cli/auto_scaling/helpers.py
e2e_cli/bucket_store/__init__.py
e2e_cli/bucket_store/bucket_routing.py
e2e_cli/bucket_store/bucket_actions/__init__.py
e2e_cli/bucket_store/bucket_actions/bucket_actions.py
e2e_cli/bucket_store/bucket_actions/helpers.py
e2e_cli/bucket_store/bucket_crud/__init__.py
e2e_cli/bucket_store/bucket_crud/bucket_storage.py
e2e_cli/bucket_store/bucket_crud/helpers.py
e2e_cli/cdn/__init__.py
e2e_cli/cdn/cdn_routing.py
e2e_cli/cdn/cdn_actions/__init__.py
e2e_cli/cdn/cdn_actions/cdn_action.py
e2e_cli/cdn/cdn_actions/helpers.py
e2e_cli/cdn/cdn_crud/__init__.py
e2e_cli/cdn/cdn_crud/cdn.py
e2e_cli/cdn/cdn_crud/helpers.py
e2e_cli/config/__init__.py
e2e_cli/config/config.py
e2e_cli/config/config_routing.py
e2e_cli/config/config_service.py
e2e_cli/core/__init__.py
e2e_cli/core/alias_service.py
e2e_cli/core/apiclient.py
e2e_cli/core/constants.py
e2e_cli/core/helper_service.py
e2e_cli/core/py_manager.py
e2e_cli/core/request_service.py
e2e_cli/core/show_messages.py
e2e_cli/dbaas/__init__.py
e2e_cli/dbaas/dbaas_routing.py
e2e_cli/dbaas/dbaas_actions/__init__.py
e2e_cli/dbaas/dbaas_actions/dbaas_action.py
e2e_cli/dbaas/dbaas_actions/helpers.py
e2e_cli/dbaas/dbaas_crud/__init__.py
e2e_cli/dbaas/dbaas_crud/dbaas.py
e2e_cli/dbaas/dbaas_crud/dbaas_cli.py
e2e_cli/dbaas/dbaas_crud/dbaas_services.py
e2e_cli/dbaas/dbaas_crud/helpers.py
e2e_cli/docs/__init__.py
e2e_cli/docs/e2e_cli.1
e2e_cli/faas/__init__.py
e2e_cli/faas/constants.py
e2e_cli/faas/faas_routing.py
e2e_cli/faas/faas_service.py
e2e_cli/faas/helper_service.py
e2e_cli/faas/setup_service.py
e2e_cli/image/__init__.py
e2e_cli/image/image_routing.py
e2e_cli/image/image_crud/__init__.py
e2e_cli/image/image_crud/helpers.py
e2e_cli/image/image_crud/image.py
