Metadata-Version: 2.1
Name: e2e-cli
Version: 0.9.21
Summary: This a E2E CLI tool for myAccount
Author: Sajal&Aman@E2E_Networks_Ltd
License-File: LICENSE
Requires-Dist: prettytable
Requires-Dist: requests
Requires-Dist: setuptools
Requires-Dist: chardet
